{
  "frame": {
    "type": "FRAME",
    "name": "모바일 쇼핑몰 앱",
    "styles": ["bg-white", "flex-col", "w-[390]", "items-center", "gap-[16]"],
    "children": [
      {
        "type": "FRAME",
        "name": "상단 바",
        "styles": ["w-[390]", "flex-row", "justify-between", "items-center", "p-[16]", "bg-white", "shadow-sm", "h-auto"],
        "children": [
          {
            "type": "FRAME",
            "name": "로고",
            "styles": ["flex-row", "items-center", "gap-[8]", "h-auto", "w-auto"],
            "children": [
              {
                "type": "RECTANGLE",
                "styles": ["bg-[#FF4D4D]", "w-[24]", "h-[24]", "rounded-md"]
              },
              {
                "type": "TEXT",
                "styles": ["text-lg", "font-bold", "text-[#111827]", "w-auto"],
                "text": "쇼핑몰"
              }
            ]
          },
          {
            "type": "FRAME",
            "name": "아이콘 그룹",
            "styles": ["flex-row", "gap-[16]", "items-center", "h-auto", "w-auto"],
            "children": [
              {
                "type": "RECTANGLE",
                "styles": ["bg-[#F3F4F6]", "w-[24]", "h-[24]", "rounded-md"]
              },
              {
                "type": "RECTANGLE",
                "styles": ["bg-[#F3F4F6]", "w-[24]", "h-[24]", "rounded-md"]
              }
            ]
          }
        ]
      },
      {
        "type": "FRAME",
        "name": "검색 바",
        "styles": ["w-[390]", "flex-row", "items-center", "p-[16]", "gap-[8]", "h-auto"],
        "children": [
          {
            "type": "FRAME",
            "name": "검색 입력창",
            "styles": ["flex-row", "items-center", "gap-[8]", "p-[8]", "bg-[#F3F4F6]", "rounded-lg", "w-[358]", "h-auto"],
            "children": [
              {
                "type": "RECTANGLE",
                "styles": ["bg-[#9CA3AF]", "w-[16]", "h-[16]", "rounded-md"]
              },
              {
                "type": "TEXT",
                "styles": ["text-sm", "text-[#9CA3AF]", "w-auto"],
                "text": "상품을 검색해보세요"
              }
            ]
          }
        ]
      },
      {
        "type": "FRAME",
        "name": "배너 슬라이더",
        "styles": ["flex-row", "w-full", "h-auto", "bg-[#F9FAFB]", "rounded-lg", "p-[16]"],
        "children": [
          {
            "type": "FRAME",
            "name": "배너 내용",
            "styles": ["flex-col", "w-full", "h-auto", "justify-end"],
            "children": [
              {
                "type": "RECTANGLE",
                "styles": ["bg-[#FF8080]", "w-full", "h-[100]", "rounded-lg"]
              },
              {
                "type": "FRAME",
                "name": "배너 텍스트",
                "styles": ["flex-col", "gap-[8]", "p-[16]", "h-auto", "w-full"],
                "children": [
                  {
                    "type": "TEXT",
                    "styles": ["text-lg", "text-[#000000]", "font-bold", "w-full"],
                    "text": "여름 시즌 특별 할인"
                  },
                  {
                    "type": "TEXT",
                    "styles": ["text-sm", "text-[#000000]", "w-auto"],
                    "text": "최대 50% 할인 혜택을 놓치지 마세요!"
                  }
                ]
              }
            ]
          }
        ]
      },
      {
        "type": "FRAME",
        "name": "카테고리 메뉴",
        "styles": ["w-[390]", "flex-row", "justify-between", "p-[16]", "h-auto"],
        "children": [
          {
            "type": "FRAME",
            "name": "카테고리 아이템",
            "styles": ["flex-col", "items-center", "gap-[8]", "h-auto", "w-auto"],
            "children": [
              {
                "type": "ELLIPSE",
                "styles": ["bg-[#F3F4F6]", "w-[48]", "h-[48]"]
              },
              {
                "type": "TEXT",
                "styles": ["text-xs", "text-[#111827]", "w-auto", "text-center"],
                "text": "의류"
              }
            ]
          },
          {
            "type": "FRAME",
            "name": "카테고리 아이템",
            "styles": ["flex-col", "items-center", "gap-[8]", "h-auto", "w-auto"],
            "children": [
              {
                "type": "ELLIPSE",
                "styles": ["bg-[#F3F4F6]", "w-[48]", "h-[48]"]
              },
              {
                "type": "TEXT",
                "styles": ["text-xs", "text-[#111827]", "w-auto", "text-center"],
                "text": "신발"
              }
            ]
          },
          {
            "type": "FRAME",
            "name": "카테고리 아이템",
            "styles": ["flex-col", "items-center", "gap-[8]", "h-auto", "w-auto"],
            "children": [
              {
                "type": "ELLIPSE",
                "styles": ["bg-[#F3F4F6]", "w-[48]", "h-[48]"]
              },
              {
                "type": "TEXT",
                "styles": ["text-xs", "text-[#111827]", "w-auto", "text-center"],
                "text": "가방"
              }
            ]
          },
          {
            "type": "FRAME",
            "name": "카테고리 아이템",
            "styles": ["flex-col", "items-center", "gap-[8]", "h-auto", "w-auto"],
            "children": [
              {
                "type": "ELLIPSE",
                "styles": ["bg-[#F3F4F6]", "w-[48]", "h-[48]"]
              },
              {
                "type": "TEXT",
                "styles": ["text-xs", "text-[#111827]", "w-auto", "text-center"],
                "text": "액세서리"
              }
            ]
          },
          {
            "type": "FRAME",
            "name": "카테고리 아이템",
            "styles": ["flex-col", "items-center", "gap-[8]", "h-auto", "w-auto"],
            "children": [
              {
                "type": "ELLIPSE",
                "styles": ["bg-[#F3F4F6]", "w-[48]", "h-[48]"]
              },
              {
                "type": "TEXT",
                "styles": ["text-xs", "text-[#111827]", "w-auto", "text-center"],
                "text": "더보기"
              }
            ]
          }
        ]
      },
      {
        "type": "FRAME",
        "name": "섹션 헤더",
        "styles": ["w-[390]", "flex-row", "justify-between", "items-center", "p-[16]", "h-auto"],
        "children": [
          {
            "type": "TEXT",
            "styles": ["text-md", "text-[#111827]", "font-bold", "w-auto"],
            "text": "인기 상품"
          },
          {
            "type": "TEXT",
            "styles": ["text-sm", "text-[#FF4D4D]", "w-auto"],
            "text": "더보기"
          }
        ]
      },
      {
        "type": "FRAME",
        "name": "인기 상품 그리드",
        "styles": ["w-[390]", "flex-row", "flex-wrap", "p-[16]", "gap-[16]", "h-auto"],
        "children": [
          {
            "type": "FRAME",
            "name": "상품 카드",
            "styles": ["flex-col", "gap-[8]", "w-[170]", "h-auto"],
            "children": [
              {
                "type": "RECTANGLE",
                "styles": ["bg-[#F3F4F6]", "w-[170]", "h-[170]", "rounded-lg"]
              },
              {
                "type": "TEXT",
                "styles": ["text-sm", "text-[#111827]", "w-auto"],
                "text": "여름용 티셔츠"
              },
              {
                "type": "TEXT",
                "styles": ["text-md", "text-[#111827]", "font-bold", "w-auto"],
                "text": "29,000원"
              },
              {
                "type": "FRAME",
                "name": "평점",
                "styles": ["flex-row", "items-center", "gap-[4]", "h-auto", "w-auto"],
                "children": [
                  {
                    "type": "RECTANGLE",
                    "styles": ["bg-[#FBBF24]", "w-[12]", "h-[12]", "rounded-sm"]
                  },
                  {
                    "type": "TEXT",
                    "styles": ["text-xs", "text-[#6B7280]", "w-auto"],
                    "text": "4.8 (120)"
                  }
                ]
              }
            ]
          },
          {
            "type": "FRAME",
            "name": "상품 카드",
            "styles": ["flex-col", "gap-[8]", "w-[170]", "h-auto"],
            "children": [
              {
                "type": "RECTANGLE",
                "styles": ["bg-[#F3F4F6]", "w-[170]", "h-[170]", "rounded-lg"]
              },
              {
                "type": "TEXT",
                "styles": ["text-sm", "text-[#111827]", "w-auto"],
                "text": "캐주얼 청바지"
              },
              {
                "type": "TEXT",
                "styles": ["text-md", "text-[#111827]", "font-bold", "w-auto"],
                "text": "49,000원"
              },
              {
                "type": "FRAME",
                "name": "평점",
                "styles": ["flex-row", "items-center", "gap-[4]", "h-auto", "w-auto"],
                "children": [
                  {
                    "type": "RECTANGLE",
                    "styles": ["bg-[#FBBF24]", "w-[12]", "h-[12]", "rounded-sm"]
                  },
                  {
                    "type": "TEXT",
                    "styles": ["text-xs", "text-[#6B7280]", "w-auto"],
                    "text": "4.7 (98)"
                  }
                ]
              }
            ]
          }
        ]
      },
      {
        "type": "FRAME",
        "name": "섹션 헤더",
        "styles": ["w-[390]", "flex-row", "justify-between", "items-center", "p-[16]", "mt-[16]", "h-auto"],
        "children": [
          {
            "type": "TEXT",
            "styles": ["text-md", "text-[#111827]", "font-bold", "w-auto"],
            "text": "신상품"
          },
          {
            "type": "TEXT",
            "styles": ["text-sm", "text-[#FF4D4D]", "w-auto"],
            "text": "더보기"
          }
        ]
      },
      {
        "type": "FRAME",
        "name": "신상품 리스트",
        "styles": ["w-[390]", "flex-col", "p-[16]", "gap-[16]", "h-auto"],
        "children": [
          {
            "type": "FRAME",
            "name": "상품 리스트 아이템",
            "styles": ["flex-row", "gap-[16]", "w-full", "h-auto"],
            "children": [
              {
                "type": "RECTANGLE",
                "styles": ["bg-[#F3F4F6]", "w-[80]", "h-[80]", "rounded-lg"]
              },
              {
                "type": "FRAME",
                "name": "상품 정보",
                "styles": ["flex-col", "justify-center", "gap-[4]", "h-full", "w-full"],
                "children": [
                  {
                    "type": "TEXT",
                    "styles": ["text-sm", "text-[#111827]", "w-full"],
                    "text": "여름 원피스"
                  },
                  {
                    "type": "TEXT",
                    "styles": ["text-md", "text-[#111827]", "font-bold", "w-full"],
                    "text": "59,000원"
                  },
                  {
                    "type": "TEXT",
                    "styles": ["text-xs", "text-[#6B7280]", "w-full"],
                    "text": "무료배송"
                  }
                ]
              }
            ]
          },
          {
            "type": "FRAME",
            "name": "상품 리스트 아이템",
            "styles": ["flex-row", "gap-[16]", "w-full", "h-auto"],
            "children": [
              {
                "type": "RECTANGLE",
                "styles": ["bg-[#F3F4F6]", "w-[80]", "h-[80]", "rounded-lg"]
              },
              {
                "type": "FRAME",
                "name": "상품 정보",
                "styles": ["flex-col", "justify-center", "gap-[4]", "h-full", "w-full"],
                "children": [
                  {
                    "type": "TEXT",
                    "styles": ["text-sm", "text-[#111827]", "w-full"],
                    "text": "여름 샌들"
                  },
                  {
                    "type": "TEXT",
                    "styles": ["text-md", "text-[#111827]", "font-bold", "w-full"],
                    "text": "39,000원"
                  },
                  {
                    "type": "TEXT",
                    "styles": ["text-xs", "text-[#6B7280]", "w-full"],
                    "text": "무료배송"
                  }
                ]
              }
            ]
          },
          {
            "type": "FRAME",
            "name": "상품 리스트 아이템",
            "styles": ["flex-row", "gap-[16]", "w-full", "h-auto"],
            "children": [
              {
                "type": "RECTANGLE",
                "styles": ["bg-[#F3F4F6]", "w-[80]", "h-[80]", "rounded-lg"]
              },
              {
                "type": "FRAME",
                "name": "상품 정보",
                "styles": ["flex-col", "justify-center", "gap-[4]", "h-full", "w-full"],
                "children": [
                  {
                    "type": "TEXT",
                    "styles": ["text-sm", "text-[#111827]", "w-full"],
                    "text": "미니 크로스백"
                  },
                  {
                    "type": "TEXT",
                    "styles": ["text-md", "text-[#111827]", "font-bold", "w-full"],
                    "text": "45,000원"
                  },
                  {
                    "type": "TEXT",
                    "styles": ["text-xs", "text-[#6B7280]", "w-full"],
                    "text": "무료배송"
                  }
                ]
              }
            ]
          }
        ]
      },
      {
        "type": "FRAME",
        "name": "하단 네비게이션",
        "styles": ["w-[390]", "flex-row", "justify-between", "items-center", "p-[32]", "bg-white", "shadow-sm", "h-auto"],
        "children": [
          {
            "type": "FRAME",
            "name": "네비게이션 아이템",
            "styles": ["flex-col", "items-center", "gap-[4]", "h-auto", "w-auto"],
            "children": [
              {
                "type": "RECTANGLE",
                "styles": ["bg-[#FF4D4D]", "w-[24]", "h-[24]", "rounded-sm"]
              },
              {
                "type": "TEXT",
                "styles": ["text-xs", "text-[#FF4D4D]", "w-auto", "text-center"],
                "text": "홈"
              }
            ]
          },
          {
            "type": "FRAME",
            "name": "네비게이션 아이템",
            "styles": ["flex-col", "items-center", "gap-[4]", "h-auto", "w-auto"],
            "children": [
              {
                "type": "RECTANGLE",
                "styles": ["bg-[#9CA3AF]", "w-[24]", "h-[24]", "rounded-sm"]
              },
              {
                "type": "TEXT",
                "styles": ["text-xs", "text-[#9CA3AF]", "w-auto", "text-center"],
                "text": "카테고리"
              }
            ]
          },
          {
            "type": "FRAME",
            "name": "네비게이션 아이템",
            "styles": ["flex-col", "items-center", "gap-[4]", "h-auto", "w-auto"],
            "children": [
              {
                "type": "RECTANGLE",
                "styles": ["bg-[#9CA3AF]", "w-[24]", "h-[24]", "rounded-sm"]
              },
              {
                "type": "TEXT",
                "styles": ["text-xs", "text-[#9CA3AF]", "w-auto", "text-center"],
                "text": "찜"
              }
            ]
          },
          {
            "type": "FRAME",
            "name": "네비게이션 아이템",
            "styles": ["flex-col", "items-center", "gap-[4]", "h-auto", "w-auto"],
            "children": [
              {
                "type": "RECTANGLE",
                "styles": ["bg-[#9CA3AF]", "w-[24]", "h-[24]", "rounded-sm"]
              },
              {
                "type": "TEXT",
                "styles": ["text-xs", "text-[#9CA3AF]", "w-auto", "text-center"],
                "text": "마이페이지"
              }
            ]
          }
        ]
      }
    ]
  }
} 